csv.toolkit-0.1.0-py2.7-nspkg.pth
csv/toolkit/__init__.py
csv/toolkit/scripts.py
csv/toolkit/interface/__init__.py
csv/toolkit/interface/extension.py
csv/toolkit/interface/interface.py
csv/toolkit/loaders/__init__.py
csv/toolkit/loaders/exceptions.py
csv/toolkit/loaders/loaders.py
csv/toolkit/logger/__init__.py
csv/toolkit/logger/logger.py
csv/toolkit/validation/__init__.py
csv/toolkit/validation/exceptions.py
csv/toolkit/validation/tool.py
csv/toolkit/validation/validation.py
csv/toolkit/validation/validators.py
csv.toolkit-0.1.0.dist-info/DESCRIPTION.rst
csv.toolkit-0.1.0.dist-info/entry_points.txt
csv.toolkit-0.1.0.dist-info/METADATA
csv.toolkit-0.1.0.dist-info/metadata.json
csv.toolkit-0.1.0.dist-info/namespace_packages.txt
csv.toolkit-0.1.0.dist-info/RECORD
csv.toolkit-0.1.0.dist-info/top_level.txt
csv.toolkit-0.1.0.dist-info/WHEEL
csv.toolkit-0.1.0.dist-info/zip-safe
