Metadata-Version: 2.0
Name: csv.toolkit
Version: 0.1.0
Summary: Tools for working with CSV files
Home-page: https://github.com/sietekk/csv.toolkit
Author: Michael Conroy
Author-email: sietekk@gmail.com
License: MIT
Keywords: csv tool validation processing
Platform: UNKNOWN
Classifier: Intended Audience :: Developers
Classifier: License :: OSI Approved :: MIT License
Classifier: Programming Language :: Python :: 2.6
Classifier: Programming Language :: Python :: 2.7
Classifier: Programming Language :: Python :: 3.2
Classifier: Programming Language :: Python :: 3.3
Classifier: Programming Language :: Python :: 3.4
Requires-Dist: six (>=1.5,<2)
Provides-Extra: dev
Requires-Dist: pbbt (>=0.1.4,<1); extra == 'dev'
Requires-Dist: coverage (>=3.7,<4); extra == 'dev'
Requires-Dist: nose (>=1.3,<2); extra == 'dev'
Requires-Dist: nosy (>=1.1,<2); extra == 'dev'
Requires-Dist: prospector[with_pyroma] (<0.13,>=0.12); extra == 'dev'
Requires-Dist: twine (>=1.5,<2); extra == 'dev'
Requires-Dist: wheel (<0.25,>=0.24); extra == 'dev'
Requires-Dist: Sphinx (>=1.3,<2); extra == 'dev'
Requires-Dist: sphinx-autobuild (>=0.5,<0.6); extra == 'dev'
Requires-Dist: tox (<3,>=2); extra == 'dev'
Requires-Dist: flake8 (>=2.5.0,<3); extra == 'dev'
